ertools/__init__.py
ertools/button.py
ertools/chatbot.py
ertools/encrypt.py
ertools/getuser.py
ertools/logger.py
ertools/misc.py
ertools/trans.py
ertools-0.2.dist-info/LICENSE
ertools-0.2.dist-info/METADATA
ertools-0.2.dist-info/WHEEL
ertools-0.2.dist-info/top_level.txt
ertools-0.2.dist-info/RECORD
