Metadata-Version: 2.1
Name: ertools
Version: 0.2
Summary: Library for Chatbot
Home-page: https://pypi.org/JustR
Author: ErNewDev0
Author-email: admin@ryppain.com
License: MIT
Classifier: Programming Language :: Python :: 3
Classifier: Programming Language :: Python :: 3.8
Classifier: Programming Language :: Python :: 3.9
Classifier: Programming Language :: Python :: 3.10
Classifier: Programming Language :: Python :: 3.11
Classifier: Programming Language :: Python :: 3.12
Classifier: License :: OSI Approved :: MIT License
Classifier: Operating System :: OS Independent
Requires-Python: >=3.8, <3.13
License-File: LICENSE
